<soap:Envelope xmlns:soap="http://schemas.xmlsoap.org/soap/envelope/">
    <soap:Body>
        <ns7:suchenKundeResponse
                xmlns="http://bom.telekom.de/svc"
                xmlns:bom="http://bom.telekom.de/cc"
                xmlns:ns1="http://schemas.telekom.net/csdg_v01.01"
                xmlns:ns2="http://services.tdeu.telekom.net/CustRelMgmt/CustomInMa/SuchenKunde_v01.00/types"
                xmlns:crmt="http://bom.telekom.de/crmt"
                xmlns:kks="http://bom.telekom.de/kks"
                xmlns:ns7="http://services.tdeu.telekom.net/CustRelMgmt/CustomInMa/SuchenKunde_v01.00">
            <ns2:context>
                <ns1:technicalContext>
                    <ns1:from>de.telekom.vvm.architecture.VVM:Default</ns1:from>
                    <ns1:routingInfo>de.telekom.vvm.architecture.VVM:Default:SuchenKunde</ns1:routingInfo>
                    <ns1:messageId>49ab77b2-3fa4-4ce1-8c01-1701d0a39845</ns1:messageId>
                    <ns1:currentSenderTimestampUTC>2019-09-17T14:48:58.171Z</ns1:currentSenderTimestampUTC>
                    <ns1:expiryOffsetInMillis>600000</ns1:expiryOffsetInMillis>
                </ns1:technicalContext>
                <ns1:businessContext>
                    <ns1:processId>894017ec-355a-46e7-a18b-1d203edaff42</ns1:processId>
                    <ns1:processTypeId>SuchenKunde</ns1:processTypeId>
                </ns1:businessContext>
            </ns2:context>
            <ns2:data>
                <suchenKundeReply>
                    <Suchergebnis>
                        <Kunde>
                            <bom:Kundennummer>2110006501</bom:Kundennummer>
                            <Kundensegment>
                                <bom:Kundensegment_OID>9</bom:Kundensegment_OID>
                            </Kundensegment>
                            <bom:GP-Nummer/>
                            <Person>
                                <Anrede>
                                    <Anrede_OID>2</Anrede_OID>
                                </Anrede>
                                <bom:Name>Karla</bom:Name>
                                <bom:Vorname>Kunde</bom:Vorname>
                                <bom:Geburtsdatum>1985-01-01</bom:Geburtsdatum>
                            </Person>
                            <Rechtsform>
                                <bom:Rechtsform_OID>18</bom:Rechtsform_OID>
                            </Rechtsform>
                            <Geschaeftspartneradresse>
                                <Adresse>
                                    <bom:Adress-ID>Ditzingen</bom:Adress-ID>
                                    <Strasze>
                                        <crmt:Straszenname>Mozartstrasse.</crmt:Straszenname>
                                    </Strasze>
                                    <Grundstueck>
                                        <bom:Hausnummer>3</bom:Hausnummer>
                                    </Grundstueck>
                                    <Postcode>
                                        <bom:Postleitzahl>71254</bom:Postleitzahl>
                                    </Postcode>
                                    <Ort>
                                        <Gemeinde>
                                            <bom:Gemeindename>Ditzingen</bom:Gemeindename>
                                        </Gemeinde>
                                    </Ort>
                                    <Land>
                                        <bom:Laenderkennzeichen>DE</bom:Laenderkennzeichen>
                                        <bom:Landesname>Deutschland</bom:Landesname>
                                    </Land>
                                </Adresse>
                                <NichtBOMElemente>
                                    <CRM-T>
                                        <crmt:AnsprechpartnerID>1-1D0-268</crmt:AnsprechpartnerID>
                                        <crmt:AdressID>22114447</crmt:AdressID>
                                    </CRM-T>
                                </NichtBOMElemente>
                            </Geschaeftspartneradresse>
                            <NichtBOMElemente>
                                <KKS>
                                    <kks:AuftraggeberID>1987654321</kks:AuftraggeberID>
                                </KKS>
                                <CRM-T>
                                    <Kundenstatus>
                                        <crmt:Kunde_Aktiv>true</crmt:Kunde_Aktiv>
                                        <crmt:Kunde_Gesperrt>false</crmt:Kunde_Gesperrt>
                                    </Kundenstatus>
                                </CRM-T>
                            </NichtBOMElemente>
                        </Kunde>
                    </Suchergebnis>
                    <ReturnCode>00</ReturnCode>
                </suchenKundeReply>
            </ns2:data>
        </ns7:suchenKundeResponse>
    </soap:Body>
</soap:Envelope>
